<?xml version="1.0" encoding="UTF-8"?>

<!--- root element **REQUIRED** -->
<root>
    <postcard>
        <front image="paddinton.jpg" locale="London, UK">Image of Paddington Bears in shop</front>
        <stamp image="firstclass.jpg" origin="UK">Second class stamp - United Kingdom</stamp>
        <!-- postcard text -->
        <content>I love marmalade!</content>
        <!-- address details -->
        <address>
            <name>Paddington Bear</name>
            <co>Mrs Brown</co>
            <street>32 Windsor Gardens</street>
            <town>Notting Hill</town>
            <county>London</county>
            <country>United Kingdom</country>
            <postcode>W9 3RG</postcode>
        </address>
    </postcard>
</root>
